cronq/__init__.py
cronq/config.py
cronq/injector.py
cronq/interval_parser.py
cronq/logsetup.py
cronq/pruner.py
cronq/queue_connection.py
cronq/rabbit_connection.py
cronq/result_aggregator.py
cronq/runner.py
cronq/utils.py
cronq/validator.py
cronq/web.py
cronq/backends/__init__.py
cronq/backends/mysql.py
cronq/logger/__init__.py
cronq/logger/handlers.py
cronq/models/__init__.py
cronq/models/base.py
cronq/models/category.py
cronq/models/event.py
cronq/models/job.py
cronq/static/css/app.css
cronq/static/css/bootstrap-responsive.css
cronq/static/css/bootstrap-responsive.min.css
cronq/static/css/bootstrap.css
cronq/static/css/bootstrap.min.css
cronq/static/img/glyphicons-halflings-white.png
cronq/static/img/glyphicons-halflings.png
cronq/static/js/bootstrap.js
cronq/static/js/bootstrap.min.js
cronq/static/js/jquery.js
cronq/static/js/moment.min.js
cronq/static/js/prism.js
cronq/templates/base.html
cronq/templates/failures.html
cronq/templates/index.html
cronq/templates/job.html
cronq/templates/run_id.html
cronq-0.27.0.dist-info/DESCRIPTION.rst
cronq-0.27.0.dist-info/METADATA
cronq-0.27.0.dist-info/RECORD
cronq-0.27.0.dist-info/WHEEL
cronq-0.27.0.dist-info/entry_points.txt
cronq-0.27.0.dist-info/metadata.json
cronq-0.27.0.dist-info/top_level.txt
cronq-0.27.0.dist-info/zip-safe
