Metadata-Version: 2.0
Name: cronq
Version: 0.27.0
Summary: A Cron-like system for running tasks
Home-page: https://github.com/seatgeek/cronq
Author: SeatGeek
Author-email: opensource@seatgeek.com
License: BSD
Keywords: cron amqp
Platform: UNKNOWN
Requires-Dist: aniso8601 (==1.3.0)
Requires-Dist: blinker (==1.4)
Requires-Dist: bugsnag (==3.3.0)
Requires-Dist: click (==6.7)
Requires-Dist: contextlib2 (==0.5.5)
Requires-Dist: coverage (==4.4.2)
Requires-Dist: cronq (==0.24.1)
Requires-Dist: Flask (==0.12.2)
Requires-Dist: haigha (==0.9.0)
Requires-Dist: itsdangerous (==0.24)
Requires-Dist: Jinja2 (==2.10)
Requires-Dist: jsonschema (==2.6.0)
Requires-Dist: MarkupSafe (==1.0)
Requires-Dist: mock (==2.0.0)
Requires-Dist: PyMySQL (==0.7.11)
Requires-Dist: python-dateutil (==2.6.1)
Requires-Dist: raven (==6.3.0)
Requires-Dist: six (==1.11.0)
Requires-Dist: SQLAlchemy (==1.1.15)
Requires-Dist: WebOb (==1.7.4)
Requires-Dist: Werkzeug (==0.12.2)
Requires-Dist: wheel (==0.30.0)
